{
  "en": [
    {
      "content": "Life is like a deck of cards. You play the hand you're dealt.",
      "author": "Unknown"
    },
    {
      "content": "A card game is a conversation between players.",
      "author": "Unknown"
    },
    {
      "content": "Strategy is knowing what to do when you don't know what to do.",
      "author": "Unknown"
    },
    {
      "content": "Every master was once a beginner who refused to give up.",
      "author": "Unknown"
    },
    {
      "content": "The joker reminds us that rules can bend when creativity leads.",
      "author": "Unknown"
    },
    {
      "content": "Patience at the table teaches patience in life.",
      "author": "Unknown"
    },
    {
      "content": "A good player reads the game, not just the cards.",
      "author": "Unknown"
    },
    {
      "content": "Learning the rules is the first step to mastering any game.",
      "author": "Unknown"
    },
    {
      "content": "Fortune favors the prepared mind at the card table.",
      "author": "Unknown"
    },
    {
      "content": "Play fair, think clearly, and enjoy the company.",
      "author": "Unknown"
    }
  ],
  "uk": [
    {
      "content": "Життя схоже на колоду карт. Граєш ті, що випали.",
      "author": "Невідомий"
    },
    {
      "content": "Карткова гра — це розмова між гравцями.",
      "author": "Невідомий"
    },
    {
      "content": "Стратегія — знати, що робити, коли не знаєш, що робити.",
      "author": "Невідомий"
    },
    {
      "content": "Кожен майстер колись був новачком, який не здавався.",
      "author": "Невідомий"
    },
    {
      "content": "Джокер нагадує, що правила можуть гнутися, коли веде творчість.",
      "author": "Невідомий"
    },
    {
      "content": "Терпіння за столом вчить терпінню в житті.",
      "author": "Невідомий"
    },
    {
      "content": "Хороший гравець читає гру, а не лише карти.",
      "author": "Невідомий"
    },
    {
      "content": "Вивчення правил — перший крок до майстерності.",
      "author": "Невідомий"
    },
    {
      "content": "Удача супроводжує підготовлений розум за столом.",
      "author": "Невідомий"
    },
    {
      "content": "Грайте чесно, думайте ясно і насолоджуйтесь компанією.",
      "author": "Невідомий"
    }
  ],
  "he": [
    {
      "content": "החיים דומים לחפיסת קלפים. משחקים את מה שחולקו לך.",
      "author": "לא ידוע"
    },
    {
      "content": "משחק קלפים הוא שיחה בין שחקנים.",
      "author": "לא ידוע"
    },
    {
      "content": "אסטרטגיה היא לדעת מה לעשות כשאינך יודע מה לעשות.",
      "author": "לא ידוע"
    },
    {
      "content": "כל מומחה היה פעם מתחיל שסירב לוותר.",
      "author": "לא ידוע"
    },
    {
      "content": "הג'וקר מזכיר לנו שכללים יכולים להתגמש כשיצירתיות מובילה.",
      "author": "לא ידוע"
    },
    {
      "content": "סבלנות ליד השולחן מלמדת סבלנות בחיים.",
      "author": "לא ידוע"
    },
    {
      "content": "שחקן טוב קורא את המשחק, לא רק את הקלפים.",
      "author": "לא ידוע"
    },
    {
      "content": "לימוד הכללים הוא הצעד הראשון לשליטה בכל משחק.",
      "author": "לא ידוע"
    },
    {
      "content": "מזל מעדיף את המוח המוכן ליד שולחן הקלפים.",
      "author": "לא ידוע"
    },
    {
      "content": "שחקו הוגן, חשבו בבהירות ותהנו מהחברה.",
      "author": "לא ידוע"
    }
  ],
  "ru": [
    {
      "content": "Жизнь похожа на колоду карт. Играешь тем, что раздали.",
      "author": "Неизвестно"
    },
    {
      "content": "Карточная игра — это разговор между игроками.",
      "author": "Неизвестно"
    },
    {
      "content": "Стратегия — знать, что делать, когда не знаешь, что делать.",
      "author": "Неизвестно"
    },
    {
      "content": "Каждый мастер когда-то был новичком, который не сдавался.",
      "author": "Неизвестно"
    },
    {
      "content": "Джокер напоминает, что правила могут гнуться, когда ведёт творчество.",
      "author": "Неизвестно"
    },
    {
      "content": "Терпение за столом учит терпению в жизни.",
      "author": "Неизвестно"
    },
    {
      "content": "Хороший игрок читает игру, а не только карты.",
      "author": "Неизвестно"
    },
    {
      "content": "Изучение правил — первый шаг к мастерству.",
      "author": "Неизвестно"
    },
    {
      "content": "Удача благоприятствует подготовленному уму за столом.",
      "author": "Неизвестно"
    },
    {
      "content": "Играйте честно, думайте ясно и наслаждайтесь компанией.",
      "author": "Неизвестно"
    }
  ],
  "ar": [
    {
      "content": "الحياة مثل مجموعة أوراق. تلعب ما يُوزَّع عليك.",
      "author": "مجهول"
    },
    {
      "content": "لعبة الورق محادثة بين اللاعبين.",
      "author": "مجهول"
    },
    {
      "content": "الاستراتيجية هي معرفة ماذا تفعل عندما لا تعرف.",
      "author": "مجهول"
    },
    {
      "content": "كل خبير كان مبتدئاً رفض الاستسلام.",
      "author": "مجهول"
    },
    {
      "content": "الجوكر يذكّرنا أن القواعد قد تتغيّر حين تقود الإبداع.",
      "author": "مجهول"
    },
    {
      "content": "الصبر على الطاولة يعلّم الصبر في الحياة.",
      "author": "مجهول"
    },
    {
      "content": "اللاعب الجيد يقرأ اللعبة لا الأوراق فقط.",
      "author": "مجهول"
    },
    {
      "content": "تعلّم القواعد هو الخطوة الأولى لإتقان أي لعبة.",
      "author": "مجهول"
    },
    {
      "content": "الحظ يحبّ العقل المستعد على طاولة الورق.",
      "author": "مجهول"
    },
    {
      "content": "العب بإنصاف، فكّر بوضوح، واستمتع بالرفقة.",
      "author": "مجهول"
    }
  ],
  "zh": [
    {
      "content": "生活就像一副牌，你只能打好发到手中的牌。",
      "author": "未知"
    },
    {
      "content": "纸牌游戏是玩家之间的对话。",
      "author": "未知"
    },
    {
      "content": "策略就是在不知所措时仍知道该怎么做。",
      "author": "未知"
    },
    {
      "content": "每位高手都曾是不肯放弃的新手。",
      "author": "未知"
    },
    {
      "content": "小丑提醒我们，创造力可以灵活变通规则。",
      "author": "未知"
    },
    {
      "content": "牌桌上的耐心也教会生活中的耐心。",
      "author": "未知"
    },
    {
      "content": "好玩家读的是局势，而不只是牌面。",
      "author": "未知"
    },
    {
      "content": "学习规则是掌握任何游戏的第一步。",
      "author": "未知"
    },
    {
      "content": "牌桌上，幸运青睐有准备的人。",
      "author": "未知"
    },
    {
      "content": "公平游戏，清晰思考，享受陪伴。",
      "author": "未知"
    }
  ],
  "fr": [
    {
      "content": "La vie ressemble à un jeu de cartes : on joue la main qu'on reçoit.",
      "author": "Inconnu"
    },
    {
      "content": "Un jeu de cartes est une conversation entre joueurs.",
      "author": "Inconnu"
    },
    {
      "content": "La stratégie, c'est savoir quoi faire quand on ne sait pas.",
      "author": "Inconnu"
    },
    {
      "content": "Tout maître fut un jour un débutant qui n'a pas abandonné.",
      "author": "Inconnu"
    },
    {
      "content": "Le joker rappelle que les règles peuvent plier sous la créativité.",
      "author": "Inconnu"
    },
    {
      "content": "La patience à la table enseigne la patience dans la vie.",
      "author": "Inconnu"
    },
    {
      "content": "Un bon joueur lit la partie, pas seulement les cartes.",
      "author": "Inconnu"
    },
    {
      "content": "Apprendre les règles est la première étape vers la maîtrise.",
      "author": "Inconnu"
    },
    {
      "content": "La chance favorise l'esprit préparé autour de la table.",
      "author": "Inconnu"
    },
    {
      "content": "Jouez fair-play, pensez clairement et profitez de la compagnie.",
      "author": "Inconnu"
    }
  ],
  "de": [
    {
      "content": "Das Leben gleicht einem Kartenspiel – man spielt die ausgeteilte Hand.",
      "author": "Unbekannt"
    },
    {
      "content": "Ein Kartenspiel ist ein Gespräch zwischen Spielern.",
      "author": "Unbekannt"
    },
    {
      "content": "Strategie heißt zu wissen, was zu tun ist, wenn man es nicht weiß.",
      "author": "Unbekannt"
    },
    {
      "content": "Jeder Meister war einmal ein Anfänger, der nicht aufgab.",
      "author": "Unbekannt"
    },
    {
      "content": "Der Joker erinnert uns, dass Regeln sich biegen können, wenn Kreativität führt.",
      "author": "Unbekannt"
    },
    {
      "content": "Geduld am Tisch lehrt Geduld im Leben.",
      "author": "Unbekannt"
    },
    {
      "content": "Ein guter Spieler liest das Spiel, nicht nur die Karten.",
      "author": "Unbekannt"
    },
    {
      "content": "Regeln lernen ist der erste Schritt zur Meisterschaft.",
      "author": "Unbekannt"
    },
    {
      "content": "Glück begünstigt den vorbereiteten Geist am Kartentisch.",
      "author": "Unbekannt"
    },
    {
      "content": "Spiele fair, denke klar und genieße die Gesellschaft.",
      "author": "Unbekannt"
    }
  ],
  "es": [
    {
      "content": "La vida es como un mazo de cartas: juegas la mano que te toca.",
      "author": "Desconocido"
    },
    {
      "content": "Un juego de cartas es una conversación entre jugadores.",
      "author": "Desconocido"
    },
    {
      "content": "La estrategia es saber qué hacer cuando no lo sabes.",
      "author": "Desconocido"
    },
    {
      "content": "Todo maestro fue alguna vez un principiante que no se rindió.",
      "author": "Desconocido"
    },
    {
      "content": "El comodín recuerda que las reglas pueden doblarse con creatividad.",
      "author": "Desconocido"
    },
    {
      "content": "La paciencia en la mesa enseña paciencia en la vida.",
      "author": "Desconocido"
    },
    {
      "content": "Un buen jugador lee la partida, no solo las cartas.",
      "author": "Desconocido"
    },
    {
      "content": "Aprender las reglas es el primer paso para dominar cualquier juego.",
      "author": "Desconocido"
    },
    {
      "content": "La fortuna favorece a la mente preparada en la mesa.",
      "author": "Desconocido"
    },
    {
      "content": "Juega limpio, piensa con claridad y disfruta la compañía.",
      "author": "Desconocido"
    }
  ],
  "ja": [
    {
      "content": "人生はトランプのよう。配られた手札で勝負する。",
      "author": "不明"
    },
    {
      "content": "カードゲームはプレイヤー同士の会話だ。",
      "author": "不明"
    },
    {
      "content": "戦略とは、わからないときに何をすべきか知ること。",
      "author": "不明"
    },
    {
      "content": "達人もかつては諦めなかった初心者だった。",
      "author": "不明"
    },
    {
      "content": "ジョーカーは創造性が導くとき、ルールも曲がることを教える。",
      "author": "不明"
    },
    {
      "content": "テーブルでの忍耐は人生の忍耐を教える。",
      "author": "不明"
    },
    {
      "content": "上手なプレイヤーはカードだけでなくゲーム全体を読む。",
      "author": "不明"
    },
    {
      "content": "ルールを学ぶことが、どんなゲームも極める第一歩。",
      "author": "不明"
    },
    {
      "content": "幸運は準備された心に味方する。",
      "author": "不明"
    },
    {
      "content": "公正に、冷静に、そして仲間を楽しもう。",
      "author": "不明"
    }
  ]
}
